{"stat.useItem.minecraft.golden_apple":1,"stat.useItem.minecraft.splash_potion":45,"stat.flyOneCm":16445,"stat.walkOneCm":8933,"stat.jump":25,"stat.swimOneCm":4819,"stat.playOneMinute":3534,"stat.fallOneCm":209,"stat.leaveGame":1,"stat.sneakTime":50,"stat.damageDealt":2124,"stat.crouchOneCm":67,"stat.timeSinceDeath":3534,"stat.mobKills":32,"stat.sprintOneCm":2065,"stat.useItem.minecraft.spawn_egg":33,"stat.mineBlock.minecraft.tallgrass":4,"stat.useItem.minecraft.diamond_sword":39,"stat.diveOneCm":3204,"stat.pickup.dreammobs.fiery_heart":16}